{
    "0": {
        "author": "43360446",
        "time": "2023-02-28 10:05",
        "content": [
            "[s:a2:偷吃][s:a2:偷吃][s:a2:偷吃]",
            "",
            "[img]./mon_202302/28/-4qiozQ2r-kvukZkT3cShs-om.jpg.medium.jpg[/img]"
        ]
    },
    "1": {
        "author": "1028826",
        "time": "2023-02-28 10:06",
        "content": [
            "哥哥，我要来了[s:a2:偷吃]"
        ]
    },
    "2": {
        "author": "21086729",
        "time": "2023-02-28 10:06",
        "content": [
            "fire in the hole！"
        ]
    },
    "3": {
        "author": "64183971",
        "time": "2023-02-28 10:07",
        "content": [
            "加快加快不要停不要停同时拿起我手指头吸吮"
        ]
    },
    "4": {
        "author": "583275",
        "time": "2023-02-28 10:07",
        "content": [
            "一库一库"
        ]
    },
    "5": {
        "author": "1164963",
        "time": "2023-02-28 10:07",
        "content": [
            "怎么这么硬啊！？"
        ]
    },
    "6": {
        "author": "62562174",
        "time": "2023-02-28 10:07",
        "content": [
            "加大力度，我先插个眼在这里[s:ac:羞]"
        ]
    },
    "7": {
        "author": "63274675",
        "time": "2023-02-28 10:07",
        "content": [
            "yes，yes，o，yes"
        ]
    },
    "8": {
        "author": "60635957",
        "time": "2023-02-28 10:07",
        "content": [
            "前排插眼，火钳刘明"
        ]
    },
    "9": {
        "author": "-1",
        "time": "2023-02-28 10:08",
        "content": [
            "almost there! *N",
            "",
            "",
            "外国女友，RPG死妈"
        ]
    },
    "10": {
        "author": "61735469",
        "time": "2023-02-28 10:08",
        "content": [
            "你是一个一个一个一个。。哼啊 啊啊啊"
        ]
    },
    "11": {
        "author": "242167",
        "time": "2023-02-28 10:08",
        "content": [
            "只会捂着脸哆嗦"
        ]
    },
    "12": {
        "author": "17194354",
        "time": "2023-02-28 10:08",
        "content": [
            "枫哥不是改名什么柠檬了吗，新造型拍的老难看了"
        ]
    },
    "13": {
        "author": "61021301",
        "time": "2023-02-28 10:08",
        "content": [
            "还说得出话来？？？",
            "",
            "什么星级技师"
        ]
    },
    "14": {
        "author": "9646387",
        "time": "2023-02-28 10:09",
        "content": [
            "总有一天，我的生命将抵达终点",
            "",
            "而你，将加冕为王 [s:ac:哭笑]"
        ]
    },
    "15": {
        "author": "26972440",
        "time": "2023-02-28 10:10",
        "content": [
            "啊 啊 啊 要到了 到了 啊 呜呜呜啊啊"
        ]
    },
    "16": {
        "author": "64883967",
        "time": "2023-02-28 10:11",
        "content": [
            "比较有印象的有",
            "",
            "啊～顶到了",
            "",
            "",
            "啊～太深了～",
            "",
            "",
            "行，嗯，我准备好了～",
            "",
            "",
            "就上面的比较有印象……",
            "",
            "最多的时候是啥也不说，表情扭曲……"
        ]
    },
    "17": {
        "author": "24651510",
        "time": "2023-02-28 10:11",
        "content": [
            "老公 艹死我"
        ]
    },
    "19": {
        "author": "42733350",
        "time": "2023-02-28 10:12",
        "content": [
            "虽然我还单身，但我想到了森下下士的场景[s:ac:哭笑]“没有劲！重来！”"
        ]
    },
    "20": {
        "author": "42289334",
        "time": "2023-02-28 10:12",
        "content": [
            "给妈妈，给妈妈吧[s:ac:瞎]"
        ]
    },
    "21": {
        "author": "42853001",
        "time": "2023-02-28 10:12",
        "content": [
            "我快尿了！我不行了！"
        ]
    },
    "22": {
        "author": "-1",
        "time": "2023-02-28 10:12",
        "content": [
            "就会嗯嗯啊啊的，和刚开始时候不一样。",
            "",
            "",
            "然后每次想忍着多玩一会，都忍不住，最后就大吼几声，不动了？休息一两分钟就会催了，你还多久，搞快点。[s:ac:哭笑][s:ac:哭笑][s:ac:哭笑]"
        ]
    },
    "23": {
        "author": "64192897",
        "time": "2023-02-28 10:12",
        "content": [
            "水区经典：“射给妈妈”"
        ]
    },
    "24": {
        "author": "62890144",
        "time": "2023-02-28 10:12",
        "content": [
            "哎呀妈呀，你可整死我了，太得劲了"
        ]
    },
    "25": {
        "author": "64285219",
        "time": "2023-02-28 10:12",
        "content": [
            "[b]Reply to [pid=675548000,35513181,1]Reply[/pid] Post by [uid]#anony_1e42db35d5bca6aad6f869c419339c5f[/uid][color=gray](9楼)[/color] (2023-02-28 10:08)[/b]省略的N是啥意思"
        ]
    },
    "26": {
        "author": "258816",
        "time": "2023-02-28 10:12",
        "content": [
            "我得眼前一片黑暗"
        ]
    },
    "27": {
        "author": "34006237",
        "time": "2023-02-28 10:13",
        "content": [
            "你们这是自寻死路！"
        ]
    },
    "28": {
        "author": "-2",
        "time": "2023-02-28 10:13",
        "content": [
            "快了快了嗯嗯啊啊",
            "",
            "一边说一边大喘气一边抖",
            "",
            "到了的时候突然浑身颤抖挺腰然后软在怀里"
        ]
    },
    "29": {
        "author": "40621963",
        "time": "2023-02-28 10:13",
        "content": [
            "我老公呢"
        ]
    },
    "30": {
        "author": "62875927",
        "time": "2023-02-28 10:13",
        "content": [
            "哼哼哼  啊--啊--  啊啊啊啊"
        ]
    },
    "31": {
        "author": "64027560",
        "time": "2023-02-28 10:14",
        "content": [
            "我不行了，快点，我老公马上回来了。。。"
        ]
    },
    "32": {
        "author": "62943765",
        "time": "2023-02-28 10:14",
        "content": [
            "[quote][pid=675548995,35513181,2]Reply[/pid] [b]Post by [uid=64192897]朱七锤[/uid] (2023-02-28 10:12):[/b]",
            "",
            "",
            "水区经典：“射给妈妈”[/quote]",
            "",
            "",
            "老哥，有截图和全贴吗？"
        ]
    },
    "33": {
        "author": "62802457",
        "time": "2023-02-28 10:14",
        "content": [
            "老公，给我，射给我[s:ac:喘]"
        ]
    },
    "34": {
        "author": "10686026",
        "time": "2023-02-28 10:15",
        "content": [
            "不行了、不行了，我会叫大声的，停停停。然后就抖了"
        ]
    },
    "35": {
        "author": "3458516",
        "time": "2023-02-28 10:15",
        "content": [
            "每个人不一样吧[s:ac:瞎]",
            "",
            "有的说：来了来了，啊…就像窒息一样，然后就开始浑身发抖。",
            "",
            "还有的说：好硬啊，哥哥…天呐[s:ac:瞎]",
            "",
            "还有一回直接开抓…然后就pen了[s:ac:瞎]"
        ]
    },
    "36": {
        "author": "5267390",
        "time": "2023-02-28 10:16",
        "content": [
            "[quote][pid=675547762,35513181,1]Reply[/pid] [b]Post by [uid=21086729]jqhsztsl[/uid] (2023-02-28 10:06):[/b]",
            "",
            "",
            "fire in the hole！[/quote]",
            "",
            "",
            "[s:ac:哭笑]卧槽，老哥稳，哈哈哈哈"
        ]
    },
    "37": {
        "author": "40703617",
        "time": "2023-02-28 10:16",
        "content": [
            "阁中帝子今何在？槛外长江空自流。"
        ]
    },
    "38": {
        "author": "43304854",
        "time": "2023-02-28 10:16",
        "content": [
            "看回复给我看摁了[s:ac:喘][s:ac:喘]"
        ]
    },
    "39": {
        "author": "38356950",
        "time": "2023-02-28 10:16",
        "content": [
            "[quote][pid=675549071,35513181,2]Reply[/pid] [b]Post by [uid=64285219]溃疡之王[/uid] (2023-02-28 10:12):[/b]",
            "",
            "",
            "省略的N是啥意思[/quote]",
            "",
            "*N，重复N遍那句话"
        ]
    },
    "40": {
        "author": "62575828",
        "time": "2023-02-28 10:17",
        "content": [
            "[quote][pid=675549102,35513181,2]Reply[/pid] [b]Post by [uid=34006237]herbavi[/uid] (2023-02-28 10:13):[/b]",
            "",
            "",
            "你们这是自寻死路！[/quote]",
            "",
            "",
            "虽然但是",
            "",
            "你们[s:ac:咦]"
        ]
    },
    "41": {
        "author": "14737151",
        "time": "2023-02-28 10:18",
        "content": [
            "我不行了，快涩我苕皮里[s:ac:怕]"
        ]
    },
    "42": {
        "author": "63047532",
        "time": "2023-02-28 10:18",
        "content": [
            "[quote][pid=675548000,35513181,1]Reply[/pid] [b]Post by [uid]#anony_1e42db35d5bca6aad6f869c419339c5f[/uid][color=gray](9楼)[/color] (2023-02-28 10:08):[/b]",
            "",
            "",
            "almost there! *N",
            "",
            "",
            "外国女友，RPG死妈[/quote]",
            "",
            "",
            "牛逼！"
        ]
    },
    "43": {
        "author": "176696",
        "time": "2023-02-28 10:18",
        "content": [
            "你们是不是专业写刘备文的？"
        ]
    },
    "44": {
        "author": "1375086",
        "time": "2023-02-28 10:21",
        "content": [
            "这帖子看的好hard"
        ]
    },
    "46": {
        "author": "21750344",
        "time": "2023-02-28 10:26",
        "content": [
            "这帖子能活过今天不",
            "",
            "上一次活了好几天"
        ]
    },
    "47": {
        "author": "13013265",
        "time": "2023-02-28 10:28",
        "content": [
            "不要再超了，苕皮要被超坏了，球球了粑粑"
        ]
    },
    "48": {
        "author": "62972057",
        "time": "2023-02-28 10:31",
        "content": [
            "歪日他嘚，中啊快点设[s:a2:doge]"
        ]
    },
    "49": {
        "author": "64285219",
        "time": "2023-02-28 10:32",
        "content": [
            "[b]Reply to [pid=675549973,35513181,2]Reply[/pid] Post by [uid=38356950]卡西莫多340[/uid] (2023-02-28 10:16)[/b]羡慕了，天生喜欢洋马"
        ]
    },
    "51": {
        "author": "94182",
        "time": "2023-02-28 10:37",
        "content": [
            "好像就是要到了，快一点，啊啊啊啊"
        ]
    },
    "52": {
        "author": "62498529",
        "time": "2023-02-28 10:38",
        "content": [
            "我不好说…每一任对象们都不大一样，大部分是就哼哼，偶有骚话的"
        ]
    },
    "53": {
        "author": "64787620",
        "time": "2023-02-28 10:39",
        "content": [
            "吃饭了嘛？"
        ]
    },
    "54": {
        "author": "61383899",
        "time": "2023-02-28 10:42",
        "content": [
            "i am cuming"
        ]
    },
    "55": {
        "author": "10349394",
        "time": "2023-02-28 10:42",
        "content": [
            "I'M gonna come,I'm gonna come.",
            "",
            "",
            "Did it man,come in my ass",
            "",
            "",
            "",
            "我想起了这张gif"
        ]
    },
    "56": {
        "author": "43309614",
        "time": "2023-02-28 10:49",
        "content": [
            "老公，我想尿尿～",
            "",
            "你怎么那么猛！",
            "",
            "我要来了！！！"
        ]
    },
    "57": {
        "author": "715021",
        "time": "2023-02-28 10:49",
        "content": [
            "爸爸不要 爸爸 不要"
        ]
    },
    "58": {
        "author": "63894736",
        "time": "2023-02-28 10:55",
        "content": [
            "哼哼哼，啊 啊啊 哈啊啊啊(超大声)"
        ]
    },
    "59": {
        "author": "787907",
        "time": "2023-02-28 10:56",
        "content": [
            "哥哥，说你爱我，啊啊，我要高潮了"
        ]
    },
    "60": {
        "author": "63635404",
        "time": "2023-02-28 11:00",
        "content": [
            "你进来了吗？",
            "",
            "不，我结束了！"
        ]
    },
    "61": {
        "author": "62238938",
        "time": "2023-02-28 11:04",
        "content": [
            "平时都叫XXX爸，只有那个时候才叫我老公。"
        ]
    },
    "62": {
        "author": "39384425",
        "time": "2023-02-28 11:06",
        "content": [
            "我老婆喊救命[s:ac:哭笑]"
        ]
    },
    "63": {
        "author": "39189323",
        "time": "2023-02-28 11:07",
        "content": [
            "我的眼前一亮黑暗[s:ac:茶]"
        ]
    },
    "64": {
        "author": "3508289",
        "time": "2023-02-28 11:09",
        "content": [
            "能说出话来的。。都是演的"
        ]
    },
    "65": {
        "author": "42964447",
        "time": "2023-02-28 11:09",
        "content": [
            "[quote][pid=675548995,35513181,2]Reply[/pid] [b]Post by [uid=64192897]朱七锤[/uid] (2023-02-28 10:12):[/b]",
            "",
            "",
            "水区经典：“射给妈妈”[/quote]",
            "",
            "",
            "[img]./mon_202302/28/-4qiozQ2r-7943ZbT3cSu0-ts.jpg[/img]",
            "",
            "说的是这种吗[s:ac:哭笑]"
        ]
    },
    "66": {
        "author": "42663896",
        "time": "2023-02-28 11:10",
        "content": [
            "哈啊哈啊哈啊哈啊哈啊哈啊不要了太刺激了我想尿尿"
        ]
    },
    "67": {
        "author": "39507964",
        "time": "2023-02-28 11:10",
        "content": [
            "啊啊啊啊啊啊啊啊啊啊",
            "",
            "我好了，，不要了",
            "",
            "你快出来，，还不射 好烦啊",
            "",
            "我继续猛输出"
        ]
    },
    "68": {
        "author": "62798734",
        "time": "2023-02-28 11:13",
        "content": [
            "艹死我",
            "",
            "",
            "zsbd"
        ]
    },
    "69": {
        "author": "62307987",
        "time": "2023-02-28 11:13",
        "content": [
            "[quote][pid=675548995,35513181,2]Reply[/pid] [b]Post by [uid=64192897]朱七锤[/uid] (2023-02-28 10:12):[/b]",
            "",
            "",
            "水区经典：“射给妈妈”[/quote]",
            "",
            "",
            "这个我也顶不住啊"
        ]
    },
    "70": {
        "author": "43131765",
        "time": "2023-02-28 11:16",
        "content": [
            "悲伤的故事，boss貌似没达到过终点，每次都是说想尿尿就没后续了"
        ]
    },
    "72": {
        "author": "64192897",
        "time": "2023-02-28 11:25",
        "content": [
            "[quote][pid=675549426,35513181,2]Reply[/pid] [b]Post by [uid=62943765]我终于来玩了[/uid] (2023-02-28 10:14):[/b]",
            "",
            "",
            "老哥，有截图和全贴吗？[/quote]",
            "",
            "",
            "看65楼"
        ]
    },
    "73": {
        "author": "63680234",
        "time": "2023-02-28 11:28",
        "content": [
            "艾玛，你刮得老娘老爽了，这大勾巴"
        ]
    },
    "74": {
        "author": "60493818",
        "time": "2023-02-28 11:31",
        "content": [
            "[s:ac:喘] 快点咬我一口"
        ]
    },
    "75": {
        "author": "1213162",
        "time": "2023-02-28 11:32",
        "content": [
            "精彩故事会[s:ac:哭笑]"
        ]
    },
    "76": {
        "author": "-1",
        "time": "2023-02-28 11:37",
        "content": [
            "[quote][pid=675563582,35513181,4]Reply[/pid] [b]Post by [uid=43131765]Tyriony818[/uid] (2023-02-28 11:16):[/b]",
            "",
            "",
            "悲伤的故事，boss貌似没达到过终点，每次都是说想尿尿就没后续了[/quote]",
            "",
            "",
            "我也遇到了，某些姿势下每次说想尿尿不舒服就换姿势了[s:ac:晕]"
        ]
    },
    "77": {
        "author": "8633530",
        "time": "2023-02-28 11:45",
        "content": [
            "越叫越大声，发抖，挺腰，抓床单[s:ac:喘]"
        ]
    },
    "78": {
        "author": "63747280",
        "time": "2023-02-28 11:52",
        "content": [
            "顾小暖！你很得意是不是！"
        ]
    },
    "79": {
        "author": "2497975",
        "time": "2023-02-28 12:05",
        "content": [
            "别S里面！"
        ]
    },
    "80": {
        "author": "-1",
        "time": "2023-02-28 12:17",
        "content": [
            "老公～(大喘气)老公～(大喘气)",
            "",
            "快了快了，啊(手紧紧抓着床单，下半身开始不受控制的扭动)",
            "",
            "我家boos只有用嘴会到终点，每次都要我先给她用嘴，就很烦[s:ac:呆]"
        ]
    },
    "81": {
        "author": "27428804",
        "time": "2023-02-28 12:24",
        "content": [
            "“啊不行了不行了不行了要尿尿”",
            "",
            "“啊啊我要你，射里面，射里面”",
            "",
            "“啊啊啊啊啊”"
        ]
    },
    "82": {
        "author": "42550460",
        "time": "2023-02-28 12:32",
        "content": [
            "我踏马的不信你们都能到"
        ]
    },
    "83": {
        "author": "26066559",
        "time": "2023-02-28 12:34",
        "content": [
            "一给，湘博库"
        ]
    },
    "84": {
        "author": "63090971",
        "time": "2023-02-28 12:37",
        "content": [
            "老公...老公..."
        ]
    },
    "85": {
        "author": "38750085",
        "time": "2023-02-28 12:38",
        "content": [
            "[quote][pid=675548000,35513181,1]Reply[/pid] [b]Post by [uid]#anony_1e42db35d5bca6aad6f869c419339c5f[/uid][color=gray](9楼)[/color] (2023-02-28 10:08):[/b]",
            "",
            "",
            "almost there! *N",
            "",
            "",
            "外国女友，RPG死妈[/quote]",
            "",
            "",
            "*N? nigga?"
        ]
    },
    "86": {
        "author": "23401724",
        "time": "2023-02-28 12:40",
        "content": [
            "射我逼里[s:ac:呆]"
        ]
    },
    "87": {
        "author": "42533137",
        "time": "2023-02-28 12:42",
        "content": [
            "我每次打boss，叫的时候让感觉在杀猪?"
        ]
    },
    "88": {
        "author": "60476156",
        "time": "2023-02-28 13:22",
        "content": [
            "几乎不说话",
            "",
            "就不停大口喘气",
            "",
            "脸色泛红抱紧我[s:ac:喘]"
        ]
    },
    "89": {
        "author": "390437",
        "time": "2023-02-28 13:25",
        "content": [
            "这是我不付费能看的？"
        ]
    },
    "90": {
        "author": "64882847",
        "time": "2023-02-28 13:28",
        "content": [
            "[s:ac:瞎][s:ac:瞎]能不能不要污染18岁的小朋友的心灵。"
        ]
    },
    "92": {
        "author": "39951217",
        "time": "2023-02-28 13:45",
        "content": [
            "多来点，我爱看"
        ]
    },
    "93": {
        "author": "62318028",
        "time": "2023-02-28 13:45",
        "content": [
            "说个毛线啊，小电影看多了吧"
        ]
    },
    "94": {
        "author": "38171263",
        "time": "2023-02-28 13:48",
        "content": [
            "看看这帖能活多久"
        ]
    },
    "95": {
        "author": "-2",
        "time": "2023-02-28 13:48",
        "content": [
            "哥哥 超市我 全部给我"
        ]
    },
    "96": {
        "author": "60699549",
        "time": "2023-02-28 13:49",
        "content": [
            "让她喊“爸爸艹我”[s:ac:瞎][s:a2:有何贵干][s:a2:doge]"
        ]
    },
    "97": {
        "author": "40616294",
        "time": "2023-02-28 13:52",
        "content": [
            "老公，我喷了。。。然后就是自己动"
        ]
    },
    "98": {
        "author": "61822798",
        "time": "2023-02-28 13:54",
        "content": [
            "用指甲抓我后背"
        ]
    },
    "100": {
        "author": "26353803",
        "time": "2023-02-28 14:01",
        "content": [
            "我充值了？ 这我能看[s:ac:瞎]"
        ]
    }
}